[
  { "name": "Kanai Keshav Das", "location": "Neamatpur, Asansol" },
  { "name": "Dr Tanmoy Biswas", "location": "Asansol" },
  { "name": "Niyati Chakraborty", "location": "Kalla Hospital, Asansol" },
  { "name": "Hrishikesh Maity", "location": "" },
  { "name": "Dilip Kumar Majhi", "location": "Satgram, Asansol" },
  { "name": "Palash Layak", "location": "Asansol" },
  { "name": "Jaya Maa", "location": "Burnpur" },
  { "name": "Shobha Mataji", "location": "Asansol" },
  { "name": "Bhanu Layak", "location": "Asansol" },
  { "name": "Pradeep Kumar Mandal", "location": "Asansol" },
  { "name": "Biswajit Chakraborty", "location": "Burnpur" },
  { "name": "Anil Kumar Gupta", "location": "" },
  { "name": "Madhusudan Das", "location": "Asansol" },
  { "name": "Jasmeer Singh", "location": "Ukhra, Ukhra" },
  { "name": "Kalyan Kumar Majhi", "location": "Burnpur" },
  { "name": "Dr. Giridharilal Sinha Burman", "location": "Katwa, Katwa" },
  { "name": "Ananta Ghosh", "location": "Devipur, Asansol" },
  { "name": "Anupama Dasi", "location": "Burnpur" },
  { "name": "Ganesh Singh", "location": "Sumat Pally, Asansol" },
  { "name": "Anirban Chakraborty", "location": "Asansol" },
  { "name": "Animesh Das", "location": "Kalyanpur, Asansol" },
  { "name": "Nukul Chandra Das", "location": "Pandaveswar" },
  { "name": "Raja Mukherjee", "location": "Budha, Asansol" },
  { "name": "Dharma Shiromoni", "location": "Kolkata" },
  { "name": "Anupam Thakur", "location": "Asansol" },
  { "name": "Ayan Dey", "location": "Kolkata" },
  { "name": "Aloke Hazra", "location": "Budha, Asansol" }
]
